pymlfs/__init__.py
pymlfs/kmeans.py
pymlfs-0.1.0.dist-info/LICENSE
pymlfs-0.1.0.dist-info/METADATA
pymlfs-0.1.0.dist-info/WHEEL
pymlfs-0.1.0.dist-info/RECORD
