Metadata-Version: 2.1
Name: pymlfs
Version: 0.1.0
Summary: machine learning models from scratch
License: MIT
Author: Youssef Achenchabe
Requires-Python: >=3.9,<3.13
Classifier: License :: OSI Approved :: MIT License
Classifier: Programming Language :: Python :: 3
Classifier: Programming Language :: Python :: 3.9
Classifier: Programming Language :: Python :: 3.10
Classifier: Programming Language :: Python :: 3.11
Requires-Dist: numpy (>=1.25.2)
Requires-Dist: scipy (>=1.11.2,<2.0.0)
Requires-Dist: torch (>=2.0.0,!=2.0.1)
Requires-Dist: tqdm (>=4.66.1)
